{"stats":{"minecraft:used":{"minecraft:smithing_table":1},"minecraft:crafted":{"ryanstillandtrade:iron_scythe":1,"ryanstillandtrade:gold_scythe":1,"ryanstillandtrade:diamond_scythe":1,"ryanstillandtrade:netherite_scythe":1},"minecraft:custom":{"minecraft:jump":1,"minecraft:time_since_rest":1709,"minecraft:interact_with_smithing_table":2,"minecraft:leave_game":1,"minecraft:play_time":1709,"minecraft:time_since_death":1709,"minecraft:walk_one_cm":467,"minecraft:total_world_time":1729,"minecraft:interact_with_crafting_table":2}},"DataVersion":3698}